guimplOUI/__init__.py
guimplOUI/hello_test_www.py
guimplOUI-0.0.1.dist-info/METADATA
guimplOUI-0.0.1.dist-info/WHEEL
guimplOUI-0.0.1.dist-info/top_level.txt
guimplOUI-0.0.1.dist-info/RECORD
